kona/__init__.py
kona/key_value_store.py
kona/key_value_store_dict.py
kona/key_value_store_rocksdb.py
tests/__init__.py
tests/test_key_value_store.py
tests/test_multi_process_db.py
kona-0.1.2.dist-info/LICENSE
kona-0.1.2.dist-info/METADATA
kona-0.1.2.dist-info/WHEEL
kona-0.1.2.dist-info/top_level.txt
kona-0.1.2.dist-info/RECORD
