Metadata-Version: 2.1
Name: kona
Version: 0.1.2
Summary: Convenience of key value store
Home-page: https://github.com/iconloop/kona
Author: ICONLOOP
Author-email: t_core@iconloop.com
License: UNKNOWN
Platform: UNKNOWN
Requires-Python: >=3.7.5
License-File: LICENSE
Requires-Dist: yirgachefe
Requires-Dist: lbry-rocksdb
Provides-Extra: dev
Requires-Dist: pytest ; extra == 'dev'
Requires-Dist: flake8 ; extra == 'dev'
Requires-Dist: flake8-docstrings ; extra == 'dev'
Provides-Extra: lint
Requires-Dist: flake8 ; extra == 'lint'
Requires-Dist: flake8-docstrings ; extra == 'lint'
Provides-Extra: tests
Requires-Dist: pytest ; extra == 'tests'
